clara/__init__.py
clara/transpiler/__init__.py
clara/transpiler/mlp/__init__.py
clara/transpiler/mlp/mlpc.py
clara/transpiler/mlp/mlpr.py
clara/transpiler/naive_bayes/__init__.py
clara/transpiler/naive_bayes/bernoulliNB.py
clara/transpiler/naive_bayes/categoricalNB.py
clara/transpiler/naive_bayes/complementNB.py
clara/transpiler/naive_bayes/gausianNB.py
clara/transpiler/naive_bayes/multiNB.py
clara/transpiler/pca/__init__.py
clara/transpiler/preprocessing/__init__.py
clara/transpiler/preprocessing/kernelcenter.py
clara/transpiler/preprocessing/maxabsscaler.py
clara/transpiler/preprocessing/minmax.py
clara/transpiler/preprocessing/robustscaler.py
clara/transpiler/preprocessing/stdscaler.py
clara/transpiler/svm/__init__.py
clara/transpiler/svm/linearsvc.py
clara/transpiler/svm/svc.py
clara/transpiler/svm/svr.py
clara/transpiler/tree/__init__.py
clara_transpiler-0.17.5.dist-info/LICENSE
clara_transpiler-0.17.5.dist-info/METADATA
clara_transpiler-0.17.5.dist-info/WHEEL
clara_transpiler-0.17.5.dist-info/top_level.txt
clara_transpiler-0.17.5.dist-info/RECORD
