Metadata-Version: 2.1
Name: clara-transpiler
Version: 0.17.5
Summary: UNKNOWN
Home-page: https://github.com/asergiobranco/clara
Author: Sergio Branco | The Architech
Author-email: asergio.branco@gmail.com
License: UNKNOWN
Platform: UNKNOWN
Classifier: Development Status :: 5 - Production/Stable
Classifier: Environment :: Console
Classifier: License :: OSI Approved :: Apache Software License
Classifier: Intended Audience :: Developers
Classifier: Natural Language :: English
Classifier: Programming Language :: Python :: 3
Classifier: Operating System :: OS Independent
Classifier: Topic :: Scientific/Engineering :: Artificial Intelligence
Classifier: Topic :: Software Development :: Embedded Systems
Requires-Python: >=3.4
